{
 "ticker": "ACHR",
 "as_of": "2025-05-13",
 "cik": 1824502,
 "filings": [
  {
   "accession": "0001628280-25-024755",
   "form": "10-Q",
   "filedAt": "2025-05-12"
  },
  {
   "accession": "0001628280-25-024657",
   "form": "8-K",
   "filedAt": "2025-05-12"
  },
  {
   "accession": "0001140361-25-016681",
   "form": "DEF 14A",
   "filedAt": "2025-04-30"
  },
  {
   "accession": "0001628280-25-016541",
   "form": "8-K",
   "filedAt": "2025-04-03"
  },
  {
   "accession": "0001628280-25-008625",
   "form": "8-K",
   "filedAt": "2025-02-27"
  },
  {
   "accession": "0001104659-25-011476",
   "form": "8-K",
   "filedAt": "2025-02-11"
  },
  {
   "accession": "0001213900-20-029955",
   "form": "S-1",
   "filedAt": "2020-10-02"
  }
 ]
}