{
 "ticker": "EVTL",
 "as_of": "2025-05-27",
 "cik": 1867102,
 "filings": [
  {
   "accession": "0001104659-25-052625",
   "form": "6-K",
   "filedAt": "2025-05-27"
  },
  {
   "accession": "0001104659-25-051288",
   "form": "6-K",
   "filedAt": "2025-05-21"
  },
  {
   "accession": "0001104659-25-050100",
   "form": "424B3",
   "filedAt": "2025-05-16"
  },
  {
   "accession": "0001104659-25-047570",
   "form": "F-3",
   "filedAt": "2025-05-13"
  },
  {
   "accession": "0001104659-25-047559",
   "form": "6-K",
   "filedAt": "2025-05-13"
  },
  {
   "accession": "0001104659-25-046942",
   "form": "6-K",
   "filedAt": "2025-05-12"
  },
  {
   "accession": "0001104659-25-022354",
   "form": "20-F",
   "filedAt": "2025-03-11"
  },
  {
   "accession": "0001104659-21-145446",
   "form": "424B3",
   "filedAt": "2021-12-01"
  }
 ]
}