{
 "ticker": "KSS",
 "as_of": "2025-08-27",
 "cik": 885639,
 "filings": [
  {
   "accession": "0001193125-25-189105",
   "form": "8-K",
   "filedAt": "2025-08-27"
  },
  {
   "accession": "0000950170-25-107443",
   "form": "8-K",
   "filedAt": "2025-08-12"
  },
  {
   "accession": "0000950170-25-083079",
   "form": "10-Q",
   "filedAt": "2025-06-06"
  },
  {
   "accession": "0001193125-25-132274",
   "form": "8-K",
   "filedAt": "2025-05-30"
  },
  {
   "accession": "0001193125-25-129976",
   "form": "8-K",
   "filedAt": "2025-05-29"
  },
  {
   "accession": "0001193125-25-121073",
   "form": "8-K",
   "filedAt": "2025-05-16"
  },
  {
   "accession": "0001193125-25-119951",
   "form": "8-K",
   "filedAt": "2025-05-14"
  },
  {
   "accession": "0001558370-25-004025",
   "form": "DEF 14A",
   "filedAt": "2025-03-28"
  },
  {
   "accession": "0000950131-96-005001",
   "form": "424B4",
   "filedAt": "1996-10-10"
  }
 ]
}