{
 "ticker": "OUST",
 "as_of": "2025-06-11",
 "cik": 1816581,
 "filings": [
  {
   "accession": "0001193125-25-117780",
   "form": "8-K",
   "filedAt": "2025-05-12"
  },
  {
   "accession": "0001628280-25-024281",
   "form": "10-Q",
   "filedAt": "2025-05-09"
  },
  {
   "accession": "0001193125-25-115994",
   "form": "8-K",
   "filedAt": "2025-05-08"
  },
  {
   "accession": "0001193125-25-111604",
   "form": "S-3",
   "filedAt": "2025-05-02"
  },
  {
   "accession": "0001193125-25-103773",
   "form": "8-K",
   "filedAt": "2025-04-29"
  },
  {
   "accession": "0001140361-25-016007",
   "form": "DEF 14A",
   "filedAt": "2025-04-28"
  },
  {
   "accession": "0001193125-25-079079",
   "form": "8-K",
   "filedAt": "2025-04-11"
  },
  {
   "accession": "0001193125-20-209451",
   "form": "S-1",
   "filedAt": "2020-08-04"
  }
 ]
}