{
 "ticker": "PBM",
 "as_of": "2025-05-05",
 "cik": 1985062,
 "filings": [
  {
   "accession": "0001213900-25-034643",
   "form": "6-K",
   "filedAt": "2025-04-23"
  },
  {
   "accession": "0001213900-25-031060",
   "form": "6-K",
   "filedAt": "2025-04-11"
  },
  {
   "accession": "0001213900-25-027251",
   "form": "6-K",
   "filedAt": "2025-04-01"
  },
  {
   "accession": "0001013762-25-004459",
   "form": "6-K",
   "filedAt": "2025-03-31"
  },
  {
   "accession": "0001213900-25-020258",
   "form": "F-3",
   "filedAt": "2025-03-04"
  },
  {
   "accession": "0001410578-25-000062",
   "form": "424B3",
   "filedAt": "2025-01-30"
  },
  {
   "accession": "0001410578-24-001112",
   "form": "20-F",
   "filedAt": "2024-07-26"
  },
  {
   "accession": "0001104659-23-118691",
   "form": "424B3",
   "filedAt": "2023-11-15"
  }
 ]
}